zombie_escape/__about__.py
zombie_escape/__init__.py
zombie_escape/__main__.py
zombie_escape/colors.py
zombie_escape/config.py
zombie_escape/entities.py
zombie_escape/entities_constants.py
zombie_escape/export_images.py
zombie_escape/font_utils.py
zombie_escape/gameplay_constants.py
zombie_escape/input_utils.py
zombie_escape/level_blueprints.py
zombie_escape/level_constants.py
zombie_escape/localization.py
zombie_escape/models.py
zombie_escape/progress.py
zombie_escape/render_assets.py
zombie_escape/render_constants.py
zombie_escape/rng.py
zombie_escape/screen_constants.py
zombie_escape/stage_constants.py
zombie_escape/world_grid.py
zombie_escape/zombie_escape.py
zombie_escape/assets/fonts/Silkscreen-Regular.ttf
zombie_escape/assets/fonts/misaki_gothic.ttf
zombie_escape/gameplay/__init__.py
zombie_escape/gameplay/ambient.py
zombie_escape/gameplay/constants.py
zombie_escape/gameplay/footprints.py
zombie_escape/gameplay/interactions.py
zombie_escape/gameplay/layout.py
zombie_escape/gameplay/movement.py
zombie_escape/gameplay/spawn.py
zombie_escape/gameplay/state.py
zombie_escape/gameplay/survivors.py
zombie_escape/gameplay/utils.py
zombie_escape/locales/ui.en.json
zombie_escape/locales/ui.ja.json
zombie_escape/render/__init__.py
zombie_escape/render/core.py
zombie_escape/render/hud.py
zombie_escape/render/overview.py
zombie_escape/render/shadows.py
zombie_escape/screens/__init__.py
zombie_escape/screens/game_over.py
zombie_escape/screens/gameplay.py
zombie_escape/screens/settings.py
zombie_escape/screens/title.py
zombie_escape-1.14.4.dist-info/METADATA
zombie_escape-1.14.4.dist-info/WHEEL
zombie_escape-1.14.4.dist-info/entry_points.txt
zombie_escape-1.14.4.dist-info/licenses/LICENSE.txt
zombie_escape-1.14.4.dist-info/RECORD
