Metadata-Version: 2.4
Name: zombie-escape
Version: 1.14.4
Summary: Top-down zombie survival game built with pygame.
Project-URL: Homepage, https://github.com/tos-kamiya/zombie-escape
Author-email: Toshihiro Kamiya <kamiya@mbj.nifty.com>
License-Expression: MIT
License-File: LICENSE.txt
Classifier: Development Status :: 5 - Production/Stable
Classifier: License :: OSI Approved :: MIT License
Classifier: Programming Language :: Python
Classifier: Programming Language :: Python :: 3.10
Classifier: Programming Language :: Python :: 3.11
Classifier: Programming Language :: Python :: 3.12
Classifier: Programming Language :: Python :: 3.13
Classifier: Programming Language :: Python :: Implementation :: CPython
Requires-Python: >=3.10
Requires-Dist: numpy
Requires-Dist: platformdirs
Requires-Dist: pygame-ce
Requires-Dist: python-i18n
Requires-Dist: typing-extensions; python_version < '3.11'
Provides-Extra: dev
Requires-Dist: pydeps; extra == 'dev'
Requires-Dist: pyright; extra == 'dev'
Requires-Dist: pytest; extra == 'dev'
Requires-Dist: ruff; extra == 'dev'
